deconfig/__init__.py
deconfig/__version__.py
deconfig/core.py
deconfig/transformer.py
deconfig-0.1.0.dist-info/LICENSE
deconfig-0.1.0.dist-info/METADATA
deconfig-0.1.0.dist-info/WHEEL
deconfig-0.1.0.dist-info/top_level.txt
deconfig-0.1.0.dist-info/RECORD
