Metadata-Version: 2.1
Name: deconfig
Version: 0.1.0
Summary: A simple configuration library for Python
Author: ybhaw
Project-URL: Homepage, https://github.com/ybhaw/deconfig
Project-URL: Issues, https://github.com/ybhaw/deconfig/issues
Classifier: Programming Language :: Python :: 3
Classifier: License :: OSI Approved :: MIT License
Classifier: Operating System :: OS Independent
Requires-Python: >=3.8
License-File: LICENSE
